{"chunk_definitions":[{"chunk_id":"csetup_chunk","chunk_label":"setup","document_id":"1C2C164E","expansion_state":0,"options":{"engine":"r","include":false,"label":"setup"},"row":16,"row_count":1,"visible":true},{"chunk_id":"c4ukjldzo0u6k","chunk_label":"libraries","document_id":"1C2C164E","expansion_state":0,"options":{"engine":"r","label":"libraries"},"row":26,"row_count":1,"visible":true},{"chunk_id":"cz2ma21ar737e","chunk_label":"analysing the origin of the","document_id":"1C2C164E","expansion_state":0,"options":{"engine":"r","label":"analysing the origin of the"},"row":64,"row_count":1,"visible":true},{"chunk_id":"cz2x0ui5piiwy","chunk_label":"unnamed-chunk-2","document_id":"1C2C164E","expansion_state":0,"options":{"engine":"r","label":"unnamed-chunk-13"},"row":89,"row_count":1,"visible":true},{"chunk_id":"ccvzoi8mjx7pf","chunk_label":"unnamed-chunk-3","document_id":"95D7628F","expansion_state":0,"options":{"engine":"r","label":"unnamed-chunk-43"},"row":101,"row_count":1,"visible":true}],"default_chunk_options":{"echo":true,"message":false,"warning":false},"doc_write_time":1568207336,"working_dir":null}